Metadata-Version: 1.0
Name: evolutionary-py
Version: 0.19
Summary: A genetic algorithm framework for search optimization problems
Home-page: UNKNOWN
Author: Ashish Juneja
Author-email: UNKNOWN
License: UNKNOWN
Platform: UNKNOWN
